qcelemental/__init__.py
qcelemental/checkup_data/README.md
qcelemental/checkup_data/__init__.py
qcelemental/checkup_data/cfour_primary_masses.py
qcelemental/checkup_data/periodictable.py
qcelemental/checkup_data/physconst.py
qcelemental/conftest.py
qcelemental/covalent_radii.py
qcelemental/data/README.md
qcelemental/data/__init__.py
qcelemental/data/alvarez_2008_covalent_radii.py
qcelemental/data/mantina_2009_vanderwaals_radii.py
qcelemental/data/nist_2011_atomic_weights.py
qcelemental/data/nist_2014_codata.py
qcelemental/data/nist_2018_codata.py
qcelemental/datum.py
qcelemental/exceptions.py
qcelemental/info/__init__.py
qcelemental/info/cpu_info.py
qcelemental/info/data/__init__.py
qcelemental/info/data/cpu_data_blob.py
qcelemental/info/data/dft_data_blob.py
qcelemental/info/dft_info.py
qcelemental/models/__init__.py
qcelemental/models/align.py
qcelemental/models/basemodels.py
qcelemental/models/basis.py
qcelemental/models/common_models.py
qcelemental/models/molecule.py
qcelemental/models/procedures.py
qcelemental/models/results.py
qcelemental/models/types.py
qcelemental/molparse/__init__.py
qcelemental/molparse/chgmult.py
qcelemental/molparse/from_arrays.py
qcelemental/molparse/from_schema.py
qcelemental/molparse/from_string.py
qcelemental/molparse/nucleus.py
qcelemental/molparse/pubchem.py
qcelemental/molparse/regex.py
qcelemental/molparse/to_schema.py
qcelemental/molparse/to_string.py
qcelemental/molutil/__init__.py
qcelemental/molutil/align.py
qcelemental/molutil/connectivity.py
qcelemental/molutil/molecular_formula.py
qcelemental/molutil/test_molutil.py
qcelemental/periodic_table.py
qcelemental/physical_constants/__init__.py
qcelemental/physical_constants/context.py
qcelemental/physical_constants/ureg.py
qcelemental/testing.py
qcelemental/tests/__init__.py
qcelemental/tests/addons.py
qcelemental/tests/namespacemodule/dummy
qcelemental/tests/qcschema_instances/AtomicInput/dummy
qcelemental/tests/qcschema_instances/AtomicResult/dummy
qcelemental-0.30.0.dist-info/LICENSE
qcelemental-0.30.0.dist-info/METADATA
qcelemental-0.30.0.dist-info/WHEEL
qcelemental-0.30.0.dist-info/RECORD
