Metadata-Version: 2.1
Name: qcelemental
Version: 0.30.0
Summary: Core data structures for Quantum Chemistry.
Home-page: https://github.com/MolSSI/QCElemental
License: BSD-3-Clause
Author: The QCArchive Development Team
Author-email: qcarchive@molssi.org
Requires-Python: >=3.7,<3.14
Classifier: Development Status :: 4 - Beta
Classifier: Intended Audience :: Science/Research
Classifier: License :: OSI Approved :: BSD License
Classifier: Programming Language :: Python :: 3
Classifier: Programming Language :: Python :: 3.7
Classifier: Programming Language :: Python :: 3.8
Classifier: Programming Language :: Python :: 3.9
Classifier: Programming Language :: Python :: 3.10
Classifier: Programming Language :: Python :: 3.11
Classifier: Programming Language :: Python :: 3 :: Only
Classifier: Programming Language :: Python :: 3.12
Classifier: Programming Language :: Python :: 3.13
Provides-Extra: align
Provides-Extra: test
Provides-Extra: viz
Requires-Dist: importlib-metadata (>=4.8) ; python_version < "3.8"
Requires-Dist: ipykernel (<6.0.0) ; extra == "viz"
Requires-Dist: networkx (<3.0) ; extra == "align"
Requires-Dist: nglview (>=3.0.3,<4.0.0) ; extra == "viz"
Requires-Dist: numpy (>=1.12.0) ; python_version == "3.8"
Requires-Dist: numpy (>=1.26.1) ; python_version >= "3.9" and python_version < "3.14"
Requires-Dist: numpy (>=1.26.1,<2.0) ; python_version >= "3.9" and python_version < "3.10"
Requires-Dist: packaging (>=24.0) ; python_version >= "3.7" and python_version < "3.8"
Requires-Dist: packaging (>=24.1) ; python_version >= "3.8"
Requires-Dist: pint (>=0.10) ; python_version >= "3.7" and python_version < "3.9"
Requires-Dist: pint (>=0.23) ; python_version >= "3.9" and python_version < "3.10"
Requires-Dist: pint (>=0.24) ; python_version >= "3.10" and python_version < "3.14"
Requires-Dist: pydantic (>=1.8.2)
Requires-Dist: pytest (>=7.2.2,<8.0.0) ; extra == "test"
Requires-Dist: scipy (>=1.6.0) ; (python_version < "3.9") and (extra == "align")
Requires-Dist: scipy (>=1.9.0) ; (python_version >= "3.9" and python_version < "3.14") and (extra == "align")
Requires-Dist: setuptools (>=68.0.0)
Project-URL: Documentation, http://docs.qcarchive.molssi.org/projects/qcelemental/en/latest/
